gptify/.gptignore
gptify/__init__.py
gptify/cli.py
gptify/gpt_repository_loader.py
gptify-0.5.0.dist-info/LICENSE
gptify-0.5.0.dist-info/METADATA
gptify-0.5.0.dist-info/WHEEL
gptify-0.5.0.dist-info/entry_points.txt
gptify-0.5.0.dist-info/RECORD
