Metadata-Version: 2.1
Name: gptify
Version: 0.5.0
Summary: Convert code repos into an LLM prompt-friendly format. Forked from https://github.com/zackees/gptrepo
Home-page: https://github.com/ogre-run/gptify
Author: Wilder Lopes
Author-email: wilder@ogre.run
Requires-Python: >=3.9
Classifier: Programming Language :: Python :: 3
Classifier: Programming Language :: Python :: 3.9
Classifier: Programming Language :: Python :: 3.10
Classifier: Programming Language :: Python :: 3.11
Classifier: Programming Language :: Python :: 3.12
Classifier: Programming Language :: Python :: 3.13
Requires-Dist: pyperclip (>=1.8.2,<2.0.0)
Requires-Dist: tiktoken (>=0.8.0,<0.9.0)
